trackma/__init__.py
trackma/accounts.py
trackma/data/anilist.jpg
trackma/data/icon.ico
trackma/data/icon.png
trackma/data/kitsu.png
trackma/data/mal.jpg
trackma/data/shikimori.jpg
trackma/data/vndb.jpg
trackma/data.py
trackma/engine.py
trackma/extras/__init__.py
trackma/extras/redirections.py
trackma/lib/__init__.py
trackma/lib/lib.py
trackma/lib/libanilist.py
trackma/lib/libkitsu.py
trackma/lib/libmal.py
trackma/lib/libshikimori.py
trackma/lib/libvndb.py
trackma/messenger.py
trackma/parser/__init__.py
trackma/parser/animeinfoextractor.py
trackma/parser/anitopy.py
trackma/tracker/__init__.py
trackma/tracker/inotify.py
trackma/tracker/inotifyBase.py
trackma/tracker/jellyfin.py
trackma/tracker/kodi.py
trackma/tracker/mpris.py
trackma/tracker/plex.py
trackma/tracker/polling.py
trackma/tracker/pyinotify.py
trackma/tracker/tracker.py
trackma/tracker/win32.py
trackma/trackma.kdev4
trackma/ui/__init__.py
trackma/ui/cli.py
trackma/ui/curses.py
trackma/ui/gtk/__init__.py
trackma/ui/gtk/__main__.py
trackma/ui/gtk/accountswindow.py
trackma/ui/gtk/application.py
trackma/ui/gtk/data/accountrow.ui
trackma/ui/gtk/data/accountswindow.ui
trackma/ui/gtk/data/app-menu.ui
trackma/ui/gtk/data/mainview.ui
trackma/ui/gtk/data/searchwindow.ui
trackma/ui/gtk/data/settingswindow.ui
trackma/ui/gtk/data/shortcuts.ui
trackma/ui/gtk/data/showinfobox.ui
trackma/ui/gtk/data/showinfowindow.ui
trackma/ui/gtk/data/window.ui
trackma/ui/gtk/imagebox.py
trackma/ui/gtk/mainview.py
trackma/ui/gtk/searchwindow.py
trackma/ui/gtk/settingswindow.py
trackma/ui/gtk/showeventtype.py
trackma/ui/gtk/showinfobox.py
trackma/ui/gtk/showinfowindow.py
trackma/ui/gtk/showtreeview.py
trackma/ui/gtk/statusicon.py
trackma/ui/gtk/window.py
trackma/ui/qt/__init__.py
trackma/ui/qt/__main__.py
trackma/ui/qt/accounts.py
trackma/ui/qt/add.py
trackma/ui/qt/delegates.py
trackma/ui/qt/details.py
trackma/ui/qt/mainwindow.py
trackma/ui/qt/models.py
trackma/ui/qt/settings.py
trackma/ui/qt/themedcolorpicker.py
trackma/ui/qt/thumbs.py
trackma-0.9.dist-info/AUTHORS
trackma-0.9.dist-info/COPYING
trackma-0.9.dist-info/METADATA
trackma-0.9.dist-info/WHEEL
trackma-0.9.dist-info/entry_points.txt
trackma-0.9.dist-info/RECORD
