Metadata-Version: 2.3
Name: trackma
Version: 0.9
Summary: Open multi-site list manager
License: GPL-3.0-or-later
Keywords: list manager,curses,gtk,qt,myanimelist,kitsu,anilist,shikimori,vndb
Author: z411
Author-email: z411@omaera.org
Requires-Python: >=3.8,<4.0
Classifier: Development Status :: 5 - Production/Stable
Classifier: Intended Audience :: End Users/Desktop
Classifier: License :: OSI Approved :: GNU General Public License v3 or later (GPLv3+)
Classifier: Operating System :: POSIX
Classifier: Programming Language :: Python :: 3
Classifier: Programming Language :: Python :: 3.8
Classifier: Programming Language :: Python :: 3.9
Classifier: Programming Language :: Python :: 3.10
Classifier: Programming Language :: Python :: 3.11
Classifier: Programming Language :: Python :: 3.12
Classifier: Programming Language :: Python :: 3.13
Classifier: Topic :: Internet
Classifier: Topic :: Multimedia
Provides-Extra: anitopy
Provides-Extra: curses
Provides-Extra: discord-rpc
Provides-Extra: gtk
Provides-Extra: qt
Provides-Extra: trackers
Provides-Extra: twitter
Provides-Extra: ui
Requires-Dist: anitopy (>=2.0.0,<3.0.0) ; extra == "anitopy"
Requires-Dist: inotify (>=0.2.10,<0.3.0) ; extra == "trackers"
Requires-Dist: jeepney (>=0.8.0,<0.9.0) ; extra == "trackers"
Requires-Dist: pillow (>9) ; extra == "gtk" or extra == "qt" or extra == "ui"
Requires-Dist: pycairo (>=1.20.0,<2.0.0) ; extra == "gtk" or extra == "ui"
Requires-Dist: pygobject (>=3.42.1,<4.0.0) ; extra == "gtk" or extra == "ui"
Requires-Dist: pyinotify (>=0.9.6,<0.10.0) ; extra == "trackers"
Requires-Dist: pypresence (>=4.2.1,<5.0.0) ; extra == "discord-rpc"
Requires-Dist: pyqt5 (>=5.15.7,<6.0.0) ; extra == "qt" or extra == "ui"
Requires-Dist: requests (>=2.28.1,<3.0.0)
Requires-Dist: requests-oauthlib (>=1.2.0,<3.0.0) ; extra == "twitter"
Requires-Dist: twitter (>=1.19.3,<2.0.0) ; extra == "twitter"
Requires-Dist: urwid (>=2.1.2,<3.0.0) ; extra == "curses" or extra == "ui"
Project-URL: Homepage, https://z411.github.io/trackma/
Project-URL: Repository, https://github.com/z411/trackma
